mekanism/__init__.py
mekanism/errors.py
mekanism/utils.py
mekanism-1.2.dist-info/METADATA
mekanism-1.2.dist-info/WHEEL
mekanism-1.2.dist-info/licenses/LICENSE
mekanism-1.2.dist-info/RECORD
