Metadata-Version: 2.3
Name: Mekanism
Version: 1.2
Summary: Mekanism json-typed async-db by DwZZd
Project-URL: Homepage, https://github.com/DwZZd/Mekanism
Author-email: DwZZd <pppgame61@gmail.com>
License-File: LICENSE
Classifier: License :: OSI Approved :: MIT License
Classifier: Operating System :: OS Independent
Classifier: Programming Language :: Python :: 3
Requires-Python: >=3.10.0
